register_apps/VERSION
register_apps/__init__.py
register_apps/cli.py
register_apps/exceptions.py
register_apps/options.py
register_apps/utils.py
register_apps/validators.py
register_apps/data/README.md
register_apps-2.0.1.dist-info/LICENSE
register_apps-2.0.1.dist-info/METADATA
register_apps-2.0.1.dist-info/WHEEL
register_apps-2.0.1.dist-info/entry_points.txt
register_apps-2.0.1.dist-info/top_level.txt
register_apps-2.0.1.dist-info/RECORD
