Metadata-Version: 2.1
Name: register-apps
Version: 2.0.1
Summary: 👾 Register versioned toil container pipelines and other commands in singularity containers.
Home-page: https://github.com/papaemmelab/register_apps
Author: Juan S. Medina
License: BSD
Platform: UNKNOWN
Classifier: Intended Audience :: Developers
Classifier: Intended Audience :: Science/Research
Classifier: License :: OSI Approved :: MIT License
Classifier: Natural Language :: English
Classifier: Operating System :: Unix
Classifier: Operating System :: POSIX
Classifier: Programming Language :: Python :: 2 :: Only
Classifier: Topic :: Utilities
Requires-Dist: click (==6.7)
Requires-Dist: virtualenvwrapper (==4.8.2)
Provides-Extra: test
Requires-Dist: coverage (==4.4.2) ; extra == 'test'
Requires-Dist: pydocstyle (==2.1.1) ; extra == 'test'
Requires-Dist: pytest (==3.2.3) ; extra == 'test'
Requires-Dist: pytest-cov (==2.5.1) ; extra == 'test'
Requires-Dist: pytest-env (==0.6.2) ; extra == 'test'
Requires-Dist: pylint (==1.8.1) ; extra == 'test'
Requires-Dist: tox (==2.9.1) ; extra == 'test'
